Workbook

Sheet WorkbookPath
A1: Variable | B1: Value
A2: FolderPath | B2: {=LEFT(CELL("filename",A2),FIND("[",CELL("filename",A2))-1)} -> C:\Projects\largedata\code-largedata\original\src\main\resources\
A3: ReportDate | B3: 46114
A4: ReportTitle | B4: Large Data Report

Sheet Selector
A1: ModelFamily | B1: Include
A2: Family_1 | B2: O
A3: Family_10 | B3: X
A4: Family_11 | B4: X
A5: Family_12 | B5: X
A6: Family_13 | B6: X
A7: Family_14 | B7: X
A8: Family_15 | B8: X
A9: Family_16 | B9: X
A10: Family_17 | B10: X
A11: Family_18 | B11: X
A12: Family_19 | B12: X
... A33: Family_9 | B33: X

Sheet model-family
A1: id | B1: model_family | C1: report_date | D1: created_at | E1: updated_at | F1: part | G1: qty | H1: amount | I1: region_code | J1: country_code | K1: plant_code | L1: customer_code | M1: order_no | N1: lot_no | O1: serial_no | P1: status | Q1: priority | R1: sales_channel | S1: currency_code | T1: unit_price | U1: discount_amount | V1: tax_amount | W1: net_amount | X1: shipped_qty | Y1: backorder_qty | Z1: is_active
A2: 688481 | B2: Family_1 | C2: 2026-04-02 | D2: 2026-04-02 00:00:00 | E2: 2026-04-02 00:14:41 | F2: Part_81 | G2: 1 | H2: 884.81 | I2: APAC | J2: TW | K2: PLANT-05 | L2: CUST-03481 | M2: ORD-2026-00688481 | N2: LOT-08481 | O2: SN-0000688481 | P2: NEW | Q2: 1 | R2: PARTNER | S2: TWD | T2: 894.81 | U2: 44.24 | V2: 42.03 | W2: 882.60 | X2: 0 | Y2: 1 | Z2: t
A3: 875361 | B3: Family_1 | C3: 2026-04-02 | D3: 2026-04-02 00:00:00 | E3: 2026-04-02 00:09:21 | F3: Part_161 | G3: 1 | H3: 753.61 | I3: APAC | J3: TW | K3: PLANT-09 | L3: CUST-00361 | M3: ORD-2026-00875361 | N3: LOT-05361 | O3: SN-0000875361 | P3: NEW | Q3: 1 | R3: ONLINE | S3: TWD | T3: 763.61 | U3: 37.68 | V3: 35.80 | W3: 751.73 | X3: 1 | Y3: 1 | Z3: t
A4: 641761 | B4: Family_1 | C4: 2026-04-02 | D4: 2026-04-02 00:00:00 | E4: 2026-04-02 00:16:01 | F4: Part_161 | G4: 1 | H4: 417.61 | I4: APAC | J4: TW | K4: PLANT-01 | L4: CUST-01761 | M4: ORD-2026-00641761 | N4: LOT-01761 | O4: SN-0000641761 | P4: NEW | Q4: 1 | R4: DIRECT | S4: TWD | T4: 427.61 | U4: 20.88 | V4: 19.84 | W4: 416.57 | X4: 0 | Y4: 1 | Z4: t
A5: 595041 | B5: Family_1 | C5: 2026-04-02 | D5: 2026-04-02 00:00:00 | E5: 2026-04-02 00:17:21 | F5: Part_41 | G5: 1 | H5: 950.41 | I5: APAC | J5: TW | K5: PLANT-09 | L5: CUST-00041 | M5: ORD-2026-00595041 | N5: LOT-05041 | O5: SN-0000595041 | P5: NEW | Q5: 1 | R5: ONLINE | S5: TWD | T5: 960.41 | U5: 47.52 | V5: 45.14 | W5: 948.03 | X5: 1 | Y5: 1 | Z5: t
A6: 945441 | B6: Family_1 | C6: 2026-04-02 | D6: 2026-04-02 00:00:00 | E6: 2026-04-02 00:37:21 | F6: Part_41 | G6: 1 | H6: 454.41 | I6: APAC | J6: TW | K6: PLANT-09 | L6: CUST-00441 | M6: ORD-2026-00945441 | N6: LOT-05441 | O6: SN-0000945441 | P6: NEW | Q6: 1 | R6: ONLINE | S6: TWD | T6: 464.41 | U6: 22.72 | V6: 21.58 | W6: 453.27 | X6: 1 | Y6: 1 | Z6: t
A7: 665121 | B7: Family_1 | C7: 2026-04-02 | D7: 2026-04-02 00:00:00 | E7: 2026-04-02 00:45:21 | F7: Part_121 | G7: 1 | H7: 651.21 | I7: APAC | J7: TW | K7: PLANT-09 | L7: CUST-00121 | M7: ORD-2026-00665121 | N7: LOT-05121 | O7: SN-0000665121 | P7: NEW | Q7: 1 | R7: ONLINE | S7: TWD | T7: 661.21 | U7: 32.56 | V7: 30.93 | W7: 649.58 | X7: 1 | Y7: 1 | Z7: t
A8: 630081 | B8: Family_1 | C8: 2026-04-02 | D8: 2026-04-02 00:00:00 | E8: 2026-04-02 00:01:21 | F8: Part_81 | G8: 1 | H8: 300.81 | I8: APAC | J8: TW | K8: PLANT-09 | L8: CUST-00081 | M8: ORD-2026-00630081 | N8: LOT-00081 | O8: SN-0000630081 | P8: NEW | Q8: 1 | R8: ONLINE | S8: TWD | T8: 310.81 | U8: 15.04 | V8: 14.29 | W8: 300.06 | X8: 1 | Y8: 1 | Z8: t
A9: 11041 | B9: Family_1 | C9: 2026-04-02 | D9: 2026-04-02 00:00:00 | E9: 2026-04-02 00:04:01 | F9: Part_41 | G9: 1 | H9: 110.41 | I9: APAC | J9: TW | K9: PLANT-01 | L9: CUST-01041 | M9: ORD-2026-00011041 | N9: LOT-01041 | O9: SN-0000011041 | P9: NEW | Q9: 1 | R9: DIRECT | S9: TWD | T9: 120.41 | U9: 5.52 | V9: 5.24 | W9: 110.13 | X9: 0 | Y9: 1 | Z9: t
A10: 922081 | B10: Family_1 | C10: 2026-04-02 | D10: 2026-04-02 00:00:00 | E10: 2026-04-02 00:08:01 | F10: Part_81 | G10: 1 | H10: 220.81 | I10: APAC | J10: TW | K10: PLANT-01 | L10: CUST-02081 | M10: ORD-2026-00922081 | N10: LOT-02081 | O10: SN-0000922081 | P10: NEW | Q10: 1 | R10: DIRECT | S10: TWD | T10: 230.81 | U10: 11.04 | V10: 10.49 | W10: 220.26 | X10: 0 | Y10: 1 | Z10: t
A11: 781921 | B11: Family_1 | C11: 2026-04-02 | D11: 2026-04-02 00:00:00 | E11: 2026-04-02 00:12:01 | F11: Part_121 | G11: 1 | H11: 819.21 | I11: APAC | J11: TW | K11: PLANT-01 | L11: CUST-01921 | M11: ORD-2026-00781921 | N11: LOT-01921 | O11: SN-0000781921 | P11: NEW | Q11: 1 | R11: DIRECT | S11: TWD | T11: 829.21 | U11: 40.96 | V11: 38.91 | W11: 817.16 | X11: 0 | Y11: 1 | Z11: t
A12: 887041 | B12: Family_1 | C12: 2026-04-02 | D12: 2026-04-02 00:00:00 | E12: 2026-04-02 00:24:01 | F12: Part_41 | G12: 1 | H12: 870.41 | I12: APAC | J12: TW | K12: PLANT-01 | L12: CUST-02041 | M12: ORD-2026-00887041 | N12: LOT-07041 | O12: SN-0000887041 | P12: NEW | Q12: 1 | R12: DIRECT | S12: TWD | T12: 880.41 | U12: 43.52 | V12: 41.34 | W12: 868.23 | X12: 0 | Y12: 1 | Z12: t
... A86: 46081 | B86: Family_1 | C86: 2026-04-02 | D86: 2026-04-02 00:00:00 | E86: 2026-04-02 00:48:01 | F86: Part_81 | G86: 1 | H86: 460.81 | I86: APAC | J86: TW | K86: PLANT-01 | L86: CUST-01081 | M86: ORD-2026-00046081 | N86: LOT-06081 | O86: SN-0000046081 | P86: NEW | Q86: 1 | R86: DIRECT | S86: TWD | T86: 470.81 | U86: 23.04 | V86: 21.89 | W86: 459.66 | X86: 0 | Y86: 1 | Z86: t

Sheet 工作表4
A3: 774986 | B3: =VLOOKUP(A3,'model-family'!A:I,9,0) -> #N/A
A4: 751626 | B4: =VLOOKUP(A4,'model-family'!A:I,9,0) -> #N/A
A5: 763306 | B5: =VLOOKUP(A5,'model-family'!A:I,9,0) -> #N/A
A6: 856746 | B6: =VLOOKUP(A6,'model-family'!A:I,9,0) -> #N/A
A7: 810026 | B7: =VLOOKUP(A7,'model-family'!A:I,9,0) -> #N/A
A8: 786666 | B8: =VLOOKUP(A8,'model-family'!A:I,9,0) -> #N/A
A9: 646506 | B9: =VLOOKUP(A9,'model-family'!A:I,9,0) -> #N/A
A10: 845066 | B10: =VLOOKUP(A10,'model-family'!A:I,9,0) -> #N/A
A11: 938506 | B11: =VLOOKUP(A11,'model-family'!A:I,9,0) -> #N/A
A12: 868426 | B12: =VLOOKUP(A12,'model-family'!A:I,9,0) -> #N/A
A13: 704906 | B13: =VLOOKUP(A13,'model-family'!A:I,9,0) -> #N/A
A14: 4106 | B14: =VLOOKUP(A14,'model-family'!A:I,9,0) -> #N/A
... A36: 688481 | B36: =VLOOKUP(A36,'model-family'!A:I,9,0) -> APAC
